{"name":"TextKit","postlist":[{"title":"TextKit之便笺实战","slug":"iOS/TextKit之便笺实战","date":"2014-07-03T17:29:00.000Z","updated":"2018-03-28T07:42:14.000Z","comments":true,"path":"api/articles/iOS/TextKit之便笺实战.json","excerpt":null,"keywords":null,"cover":"/images/bianqian.png","content":null,"raw":null,"categories":[{"name":"iOS","path":"api/categories/iOS.json"},{"name":"控件","path":"api/categories/控件.json"}],"tags":[{"name":"TextKit","path":"api/tags/TextKit.json"},{"name":"案例","path":"api/tags/案例.json"}]},{"title":"IOS7新宠Text Kit","slug":"iOS/IOS7新宠TextKit","date":"2014-06-16T22:24:48.000Z","updated":"2018-03-28T07:42:14.000Z","comments":true,"path":"api/articles/iOS/IOS7新宠TextKit.json","excerpt":null,"keywords":null,"cover":"http://p27uwfdhv.bkt.clouddn.com/static/images/TextRenderingArchitecture-iOS6.png?imageMogr2/2/w/800","content":null,"raw":null,"categories":[{"name":"iOS","path":"api/categories/iOS.json"}],"tags":[{"name":"TextKit","path":"api/tags/TextKit.json"},{"name":"概念","path":"api/tags/概念.json"}]}]}