{"name":"脚本","postlist":[{"title":"shell命令+AppleScript脚本+Swift代码相互调用","slug":"macOS/shell命令+AppleScript脚本+Swift代码相互调用","date":"2017-02-15T17:19:30.000Z","updated":"2017-02-15T17:19:30.000Z","comments":true,"path":"api/articles/macOS/shell命令+AppleScript脚本+Swift代码相互调用.json","excerpt":null,"keywords":null,"cover":null,"content":null,"raw":null,"categories":[{"name":"macOS","path":"api/categories/macOS.json"},{"name":"JS","path":"api/categories/JS.json"}],"tags":[{"name":"语法","path":"api/tags/语法.json"},{"name":"管理","path":"api/tags/管理.json"},{"name":"混编","path":"api/tags/混编.json"},{"name":"AppleScript","path":"api/tags/AppleScript.json"},{"name":"shell","path":"api/tags/shell.json"},{"name":"脚本","path":"api/tags/脚本.json"}]},{"title":"通过沙盒中JS脚本访问其他APP","slug":"macOS/通过沙盒中JS脚本访问其他APP","date":"2017-02-14T18:25:29.000Z","updated":"2017-02-16T13:43:01.000Z","comments":true,"path":"api/articles/macOS/通过沙盒中JS脚本访问其他APP.json","excerpt":null,"keywords":null,"cover":null,"content":null,"raw":null,"categories":[{"name":"macOS","path":"api/categories/macOS.json"},{"name":"JS","path":"api/categories/JS.json"}],"tags":[{"name":"工具","path":"api/tags/工具.json"},{"name":"AppleScript","path":"api/tags/AppleScript.json"},{"name":"脚本","path":"api/tags/脚本.json"},{"name":"沙盒","path":"api/tags/沙盒.json"}]},{"title":"快速正确的安装Ruby,Rails运行环境","slug":"工具/快速正确的安装Ruby,Rails运行环境","date":"2015-01-21T23:00:39.000Z","updated":"2018-03-28T07:42:14.000Z","comments":true,"path":"api/articles/工具/快速正确的安装Ruby,Rails运行环境.json","excerpt":null,"keywords":null,"cover":null,"content":null,"raw":null,"categories":[{"name":"工具","path":"api/categories/工具.json"},{"name":"ruby","path":"api/categories/ruby.json"}],"tags":[{"name":"工具","path":"api/tags/工具.json"},{"name":"脚本","path":"api/tags/脚本.json"},{"name":"安装","path":"api/tags/安装.json"}]}]}