{"name":"设计","postlist":[{"title":"MVVM介绍","slug":"iOS/MVVM介绍","date":"2017-09-24T19:26:28.000Z","updated":"2017-10-02T22:00:42.000Z","comments":true,"path":"api/articles/iOS/MVVM介绍.json","excerpt":null,"keywords":null,"cover":"https://www.objccn.io/images/issues/issue-13/mvvm1.png","content":null,"raw":null,"categories":[{"name":"iOS","path":"api/categories/iOS.json"},{"name":"设计","path":"api/categories/设计.json"}],"tags":[]},{"title":"线程安全类的设计","slug":"iOS/线程安全类的设计","date":"2017-09-24T19:06:03.000Z","updated":"2017-09-24T19:06:03.000Z","comments":true,"path":"api/articles/iOS/线程安全类的设计.json","excerpt":null,"keywords":null,"cover":null,"content":null,"raw":null,"categories":[{"name":"iOS","path":"api/categories/iOS.json"},{"name":"设计","path":"api/categories/设计.json"}],"tags":[]}]}